pymom/PyMom.py
pymom/PyMomAbstractConsumer.py
pymom/PyMomConfig.py
pymom/PyMomConsumer.py
pymom/PyMomError.py
pymom/PyMomMessage.py
pymom/PyMomMonitor.py
pymom/PyMomProducer.py
pymom/PyMomRecoverableError.py
pymom/PyMomUnrecoverableError.py
pymom/__init__.py
pymom/__main__.py
pymom/logger.config
pymom-1.0.1.dist-info/LICENSE
pymom-1.0.1.dist-info/METADATA
pymom-1.0.1.dist-info/WHEEL
pymom-1.0.1.dist-info/top_level.txt
pymom-1.0.1.dist-info/RECORD
